{
    "created_time": "2022-02-05T06:23:16Z",
    "files": [
        {
            "attachment_folder": "",
            "created_time": "2022-02-05T06:23:16Z",
            "id": "12",
            "modified_time": "2022-02-05T06:23:16Z",
            "name": "default.html",
            "signature": "120883498588116",
            "tags": [
            ]
        },
        {
            "attachment_folder": "",
            "created_time": "2022-02-05T06:23:16Z",
            "id": "13",
            "modified_time": "2022-02-05T06:23:16Z",
            "name": "page.html",
            "signature": "99992777660372",
            "tags": [
            ]
        },
        {
            "attachment_folder": "",
            "created_time": "2022-02-05T06:23:16Z",
            "id": "14",
            "modified_time": "2022-02-05T06:23:16Z",
            "name": "post.html",
            "signature": "72273058731988",
            "tags": [
            ]
        }
    ],
    "folders": [
    ],
    "id": "11",
    "modified_time": "2022-02-05T06:23:16Z",
    "signature": "24504432465876",
    "version": 3
}
